sqre_pytravisci-0.0.4.dist-info/DESCRIPTION.rst
sqre_pytravisci-0.0.4.dist-info/METADATA
sqre_pytravisci-0.0.4.dist-info/RECORD
sqre_pytravisci-0.0.4.dist-info/WHEEL
sqre_pytravisci-0.0.4.dist-info/metadata.json
sqre_pytravisci-0.0.4.dist-info/top_level.txt
travisci/__init__.py
travisci/travisci.py
