Metadata-Version: 2.0
Name: sqre-pytravisci
Version: 0.0.4
Summary: TravisCI Python interaction class
Home-page: https://github.com/sqre-lsst/travisci
Author: Adam Thornton
Author-email: athornton@lsst.org
License: MIT
Keywords: lsst
Platform: UNKNOWN
Classifier: Development Status :: 4 - Beta
Classifier: Programming Language :: Python :: 2.7
Classifier: Programming Language :: Python :: 3.5
Classifier: License :: OSI Approved :: MIT License
Requires-Dist: sqre-apikit (>=0.1.0)
Requires-Dist: pycrypto (==2.6.1)
Requires-Dist: requests (<3.0.0,>=2.13.0)
